.gitignore
setup.py
textsimilarity/__init__.py
textsimilarity/core.py
textsimilarity.egg-info/PKG-INFO
textsimilarity.egg-info/SOURCES.txt
textsimilarity.egg-info/dependency_links.txt
textsimilarity.egg-info/not-zip-safe
textsimilarity.egg-info/requires.txt
textsimilarity.egg-info/top_level.txt
textsimilarity/templates/textsimilarity.html