Metadata-Version: 1.0
Name: textsimilarity
Version: 0.1
Summary: Compare text and get a match score
Home-page: UNKNOWN
Author: Santhosh Thottingal
Author-email: santhosh.thottingal@gmail.com
License: LGPL-3.0
Platform: UNKNOWN
